qdpy/__init__.py
qdpy/base.py
qdpy/containers.py
qdpy/experiment.py
qdpy/legacy.py
qdpy/metrics.py
qdpy/phenotype.py
qdpy/plots.py
qdpy/tools.py
qdpy/utils.py
qdpy/algorithms/__init__.py
qdpy/algorithms/base.py
qdpy/algorithms/cmame.py
qdpy/algorithms/deap.py
qdpy/algorithms/evolution.py
qdpy/algorithms/logging.py
qdpy/algorithms/sampling.py
qdpy/algorithms/search.py
qdpy/algorithms/surrogate.py
qdpy/benchmarks/__init__.py
qdpy/benchmarks/artificial_landscapes.py
qdpy/benchmarks/base.py
qdpy/containers/__init__.py
qdpy/containers/archives.py
qdpy/containers/base.py
qdpy/containers/feature_extraction.py
qdpy/containers/grids.py
qdpy/containers/populations.py
qdpy/hdsobol/__init__.py
qdpy/hdsobol/_directions.py
qdpy-0.1.2.2.dist-info/LICENSE
qdpy-0.1.2.2.dist-info/METADATA
qdpy-0.1.2.2.dist-info/WHEEL
qdpy-0.1.2.2.dist-info/top_level.txt
qdpy-0.1.2.2.dist-info/RECORD
