Metadata-Version: 2.1
Name: qdpy
Version: 0.1.2.2
Summary: Quality-Diversity algorithms in Python
Home-page: https://gitlab.com/leo.cazenille/qdpy
Author: Leo Cazenille
Author-email: leo.cazenille@gmail.com
License: LGPLv3
Keywords: optimisation,optimization,illumination,Quality-Diversity,Landscape exploration,MAP-Elites,NSLC,CVT-MAP-Elites,SAIL,evolutionary algorithms,random search
Classifier: Intended Audience :: Science/Research
Classifier: Intended Audience :: Education
Classifier: Intended Audience :: Other Audience
Classifier: Topic :: Scientific/Engineering
Classifier: Topic :: Scientific/Engineering :: Mathematics
Classifier: Topic :: Scientific/Engineering :: Artificial Intelligence
Classifier: Topic :: Scientific/Engineering :: Visualization
Classifier: Operating System :: OS Independent
Classifier: Programming Language :: Python :: 3.6
Classifier: Programming Language :: Python :: 3.7
Classifier: Programming Language :: Python :: 3.8
Classifier: Development Status :: 2 - Pre-Alpha
Classifier: Environment :: Console
Classifier: License :: OSI Approved :: GNU Lesser General Public License v3 (LGPLv3)
Requires-Python: >=3.6
License-File: LICENSE
Requires-Dist: psutil >=5.7.0
Requires-Dist: numpy >=1.15.0
Requires-Dist: scipy >=1.2.0
Requires-Dist: pandas >=0.23.0
Requires-Dist: scikit-learn >=0.24.2
Requires-Dist: matplotlib >=3.0.0
Requires-Dist: typing-extensions >=3.6.6
Requires-Dist: PyYAML >=3.13
Requires-Dist: deprecation >=2.1.0
Requires-Dist: sortedcollections >=1.2.3
Provides-Extra: all
Requires-Dist: deap >=1.2.2 ; extra == 'all'
Requires-Dist: tqdm >=4.28.1 ; extra == 'all'
Requires-Dist: colorama >=0.4.1 ; extra == 'all'
Requires-Dist: tables >=3.4.4 ; extra == 'all'
Requires-Dist: cma >=2.6.0 ; extra == 'all'
Requires-Dist: ray >=0.7.4 ; extra == 'all'
Provides-Extra: deap
Requires-Dist: deap >=1.2.2 ; extra == 'deap'
